asicloud/__init__.py
asicloud/jarvis.py
asicloud-0.1.21.dist-info/LICENSE
asicloud-0.1.21.dist-info/METADATA
asicloud-0.1.21.dist-info/WHEEL
asicloud-0.1.21.dist-info/top_level.txt
asicloud-0.1.21.dist-info/RECORD
