Metadata-Version: 2.1
Name: asicloud
Version: 0.1.21
Summary: Sun’iy intellekt uchun shaxsiy kutubxona
Home-page: https://t.me/itstimebeyond
Author: Asliddin
Author-email: erdanayevasliddin@gmail.com
License: MIT
Classifier: Programming Language :: Python :: 3
Classifier: License :: OSI Approved :: MIT License
Classifier: Operating System :: OS Independent
Requires-Python: >=3.6
License-File: LICENSE
Requires-Dist: requests
